buckinghampy/__init__.py
buckinghampy/buckingham.py
buckinghampy/nondimensional.py
buckinghampy/parameters.py
buckinghampy-1.0.dist-info/DESCRIPTION.rst
buckinghampy-1.0.dist-info/METADATA
buckinghampy-1.0.dist-info/RECORD
buckinghampy-1.0.dist-info/WHEEL
buckinghampy-1.0.dist-info/metadata.json
buckinghampy-1.0.dist-info/top_level.txt
