Metadata-Version: 2.0
Name: buckinghampy
Version: 1.0
Summary: Educational package for dimensional analysis
Home-page: https://github.com/ian-r-rose/buckinghampy
Author: Ian Rose
Author-email: ian.r.rose@gmail.com
License: GPL
Platform: Linux
Platform: Mac OS X
Platform: Windows
Classifier: Intended Audience :: Developers
Classifier: Intended Audience :: Education
Classifier: Intended Audience :: Science/Research
Classifier: Programming Language :: Python
Classifier: Programming Language :: Python :: 3
Requires-Python: >=3.6
Requires-Dist: sympy
